{
  "kind": "collectionType",
  "collectionName": "usuarios",
  "info": {
    "name": "Usuarios",
    "description": ""
  },
  "options": {
    "increments": true,
    "timestamps": true,
    "draftAndPublish": false
  },
  "pluginOptions": {},
  "attributes": {
    "nombre": {
      "type": "string"
    },
    "wallet": {
      "type": "string"
    },
    "imagenperfil": {
      "collection": "file",
      "via": "related",
      "allowedTypes": [
        "images",
        "files",
        "videos"
      ],
      "plugin": "upload",
      "required": false,
      "pluginOptions": {}
    },
    "viajes": {
      "via": "usuario",
      "collection": "viaje"
    }
  }
}
